GMM_Demux/GMM_Demux.py
GMM_Demux/GMM_IO.py
GMM_Demux/__init__.py
GMM_Demux/check_multi_comp.py
GMM_Demux/classify_drops.py
GMM_Demux/compute_venn.py
GMM_Demux/estimator.py
GMM_Demux-0.2.2.3.dist-info/LICENSE
GMM_Demux-0.2.2.3.dist-info/METADATA
GMM_Demux-0.2.2.3.dist-info/WHEEL
GMM_Demux-0.2.2.3.dist-info/entry_points.txt
GMM_Demux-0.2.2.3.dist-info/top_level.txt
GMM_Demux-0.2.2.3.dist-info/RECORD
