Metadata-Version: 2.1
Name: GMM-Demux
Version: 0.2.2.3
Summary: A multiplet removal tool for processing cell hashing data
Home-page: https://github.com/CHPGenetics/GMM-demux
Author: Hongyi Xin
Author-email: gohongyi@gmail.com
License: UNKNOWN
Platform: UNKNOWN
Classifier: Programming Language :: Python :: 3.6
Classifier: License :: OSI Approved :: MIT License
Classifier: Operating System :: OS Independent
Requires-Python: >=3.6
License-File: LICENSE
Requires-Dist: BitVector
Requires-Dist: argparse
Requires-Dist: numpy (>=1.22.4)
Requires-Dist: pandas (>=1.4.3)
Requires-Dist: scikit-learn
Requires-Dist: scipy (>=1.12.0)
Requires-Dist: statistics
Requires-Dist: tabulate
